{
  "winners": [
    "q-isl15-eifo-chai",
    "q-isl15-eifo-yashan",
    "q-isl15-ma-achal-yeled",
    "q-isl15-ma-asta",
    "q-isl15-mi-achal",
    "q-isl15-mi-bamayim"
  ],
  "missing": [],
  "narration_fail": [],
  "question_tries": [
    {
      "key": "q-isl15-mi-achal",
      "variant": 0,
      "text": "מִי אָכַל אֶת הַתַּפּוּחַ?",
      "heard": "מי אכל את התפוחה?",
      "norm": "מיאכלאתהתפוחה",
      "pass": true
    },
    {
      "key": "q-isl15-eifo-chai",
      "variant": 0,
      "text": "אֵיפֹה חַי הַלִּוְיָתָן?",
      "heard": "איפה חי הלוויתן?",
      "norm": "איפהחיהלוויתנ",
      "pass": true
    }
  ],
  "narration": [
    {
      "key": "intro-isl15",
      "text": "מִפְרַץ הַתְּמוּנוֹת. הַזֶּרֶם עִרְבֵּב אֶת הַתְּמוּנוֹת בַּמִּפְרָץ, וְעַכְשָׁו הַכֹּל מְבֻלְבָּל! אֲבָל לְיַד כֹּל תְּמוּנָה יֵשׁ מִשְׁפָּט קָטָן שֶׁמְּסַפֵּר מָה קוֹרֶה בָּהּ. אִם נִקְרָא אֶת הַמִּשְׁפָּט לְבַד — נֵדַע אֵיזוֹ תְּמוּנָה מַתְאִימָה. בּוֹאוּ נַעֲזֹר לְנוּנִי לְסַדֵּר אֶת הַמִּפְרָץ!",
      "heard": "מפרץ התמונות. הזרם ירבב את התמונות במפרץ, ועכשיו הכל מבולבל. אבל היד כל תמונה יש משפט קטן שמספר מה קורה בה. אם מקרא את המשפט לבד, נדע איזו תמונה מתאימה. בואו נעזר לנו נילסדר את המפרץ.",
      "pass": true
    },
    {
      "key": "mission-isl15-image",
      "text": "קִרְאוּ אֶת הַמִּשְׁפָּט בְּעַצְמְכֶם, בְּשֶׁקֶט — וּבַחֲרוּ אֶת הַתְּמוּנָה הַמַּתְאִימָה מִבֵּין שָׁלוֹשׁ.",
      "heard": "קראו את המשפט בעצמכם, בשקט, ובכרו את התמונה המתאימה מבין שלוש.",
      "pass": true
    },
    {
      "key": "mission-isl15-question",
      "text": "קִרְאוּ אֶת הַמִּשְׁפָּט בְּעַצְמְכֶם. הוּא נִשְׁאָר עַל הַמָּסָךְ — וְעַכְשָׁו עֲנוּ עַל הַשְּׁאֵלָה.",
      "heard": "קראו את המשפט בעצמכם, הוא נשאר על המסך, ועכשיו, אנו על השאלה.",
      "pass": true
    },
    {
      "key": "completion-isl15",
      "text": "מְצֻיָּן! קְרָאתֶם אֶת הַמִּשְׁפָּטִים לְבַד, וְהֵבַנְתֶּם כֹּל אֶחָד. מְעֻלֶּה!",
      "heard": "מצוין! קראתם את המשפטים לבד והבנתם כל אחד. מעולה!",
      "pass": true
    }
  ]
}